btsnoop/__init__.py
btsnoop/btsnoop.py
btsnoop/oui/oui.csv
btsnoop-1.0.8.dist-info/LICENSE.txt
btsnoop-1.0.8.dist-info/METADATA
btsnoop-1.0.8.dist-info/RECORD
btsnoop-1.0.8.dist-info/WHEEL
btsnoop-1.0.8.dist-info/entry_points.txt
btsnoop-1.0.8.dist-info/top_level.txt
