Metadata-Version: 2.1
Name: btsnoop
Version: 1.0.8
Summary: Parser for btsnoop file
Home-page: https://github.com/pypa/sampleproject
Author: zuolongjun
Author-email: zuolongjun@163.com
License: UNKNOWN
Project-URL: Bug Reports, https://github.com/pypa/sampleproject/issues
Project-URL: Funding, https://donate.pypi.org
Project-URL: Say Thanks!, http://saythanks.io/to/example
Project-URL: Source, https://github.com/pypa/sampleproject/
Keywords: btsnoop bluetooth bt
Platform: UNKNOWN
Classifier: Development Status :: 3 - Alpha
Classifier: Intended Audience :: Developers
Classifier: Topic :: Software Development :: Build Tools
Classifier: License :: OSI Approved :: MIT License
Classifier: Programming Language :: Python :: 3.7
Provides-Extra: test
Provides-Extra: dev
Requires-Dist: numpy
Requires-Dist: openpyxl
Requires-Dist: bitstring
Provides-Extra: dev
Requires-Dist: check-manifest; extra == 'dev'
Provides-Extra: test
Requires-Dist: coverage; extra == 'test'
